MyUI/__init__.py
MyUI/preseting.py
MyUI/ui.py
MyUI/plugins/__init__.py
MyUI/plugins/plugin_base.py
MyUI/plugins/plugin_loader.py
MyUI_pygame-1.0.9.dist-info/METADATA
MyUI_pygame-1.0.9.dist-info/WHEEL
MyUI_pygame-1.0.9.dist-info/top_level.txt
MyUI_pygame-1.0.9.dist-info/RECORD
