Metadata-Version: 2.1
Name: MyUI_pygame
Version: 1.0.9
Summary: An easy-to-use extension to the very well-known package Pygame.
Author: Neo Zetterberg
Author-email: 20091103neo@gmail.com
Classifier: Programming Language :: Python :: 3
Classifier: License :: OSI Approved :: MIT License
Classifier: Operating System :: OS Independent
Requires-Python: >=3.7
Requires-Dist: pygame
Requires-Dist: pyperclip
